Workbook

Sheet 📦 Product Catalog
A1: SLOI AI — Commodity Product Catalog v2
A2: Blue = editable input · Green = auto-calculated · Update market prices weekly · May 2026
A3: PRODUCT IDENTIFICATION | F3: PRICING (USD) | L3: LOGISTICS & PORTS | R3: TRADE TERMS | V3: VALIDITY & DATES | Y3: SETTINGS
A4: REF Code | B4: SKU | C4: Product Name | D4: Sector | E4: Unit | F4: Cost Price $/unit | G4: Market Price $/unit | H4: Broker Floor $/unit | I4: Freight $/unit | J4: CIF Price $/unit | K4: Margin % | L4: Port of Origin | M4: Port of Destination | N4: Shipping Route | O4: Lead Time (days) | P4: Incoterm | Q4: Origin Country | R4: Import Duty % | S4: Landed Cost $/unit | T4: Payment Terms | U4: Last Updated | V4: Price Valid Until | W4: Days to Expiry | X4: MOQ | Y4: Min Deal USD | Z4: Certifications | AA4: Inspection | AB4: Active
A5: REF-MET-001 | B5: STL-12 | C5: Steel Rebar G60 12mm | D5: Metals | E5: MT | F5: 2580 | G5: 2840 | H5: 2720 | I5: 45 | J5: =G5+I5 -> 2,885.00 | K5: =IFERROR(ROUND((G5-F5)/F5,4),0) -> 10.1% | L5: Jebel Ali, UAE | M5: Alexandria, Egypt | N5: =L5&" → "&M5 -> Jebel Ali, UAE → Alexandria, Egypt | O5: 7 | P5: FOB | Q5: UAE/Turkey | R5: 0.05 | S5: =J5*(1+R5) -> 3,029.25 | T5: LC at sight | U5: 46149 | V5: 46184 | W5: =V5-TODAY() -> 29 | X5: 10 | Y5: 50000 | Z5: ISO 3834, CE, ASTM A615 | AA5: SGS/BV | AB5: Yes
A6: REF-MET-001 | B6: STL-HRC | C6: Steel HR Coil SS400 | D6: Metals | E6: MT | F6: 2820 | G6: 3100 | H6: 2950 | I6: 55 | J6: =G6+I6 -> 3,155.00 | K6: =IFERROR(ROUND((G6-F6)/F6,4),0) -> 9.9% | L6: Jebel Ali, UAE | M6: Port Said, Egypt | N6: =L6&" → "&M6 -> Jebel Ali, UAE → Port Said, Egypt | O6: 10 | P6: FOB | Q6: UAE/Turkey | R6: 0.05 | S6: =J6*(1+R6) -> 3,312.75 | T6: LC at sight | U6: 46153 | V6: 46184 | W6: =V6-TODAY() -> 29 | X6: 20 | Y6: 80000 | Z6: ISO 3834, JIS G3101 | AA6: BV | AB6: Yes
A7: REF-MET-001 | B7: STL-CRC | C7: Steel CR Coil DC01 | D7: Metals | E7: MT | F7: 3100 | G7: 3400 | H7: 3220 | I7: 65 | J7: =G7+I7 -> 3,465.00 | K7: =IFERROR(ROUND((G7-F7)/F7,4),0) -> 9.7% | L7: Hamburg, Germany | M7: Jebel Ali, UAE | N7: =L7&" → "&M7 -> Hamburg, Germany → Jebel Ali, UAE | O7: 12 | P7: FOB | Q7: Germany | R7: 0 | S7: =J7*(1+R7) -> 3,465.00 | T7: LC 30 days | U7: 46154 | V7: 46168 | W7: =V7-TODAY() -> 13 | X7: 20 | Y7: 80000 | Z7: EN 10130, ISO 3834 | AA7: SGS | AB7: Yes
A8: REF-MET-002 | B8: ALU-6061 | C8: Aluminum 6061-T6 | D8: Metals | E8: MT | F8: 8400 | G8: 9200 | H8: 8800 | I8: 75 | J8: =G8+I8 -> 9,275.00 | K8: =IFERROR(ROUND((G8-F8)/F8,4),0) -> 9.5% | L8: Jebel Ali, UAE | M8: Haifa, Israel | N8: =L8&" → "&M8 -> Jebel Ali, UAE → Haifa, Israel | O8: 8 | P8: FOB | Q8: UAE/China | R8: 0 | S8: =J8*(1+R8) -> 9,275.00 | T8: TT in advance | U8: 46153 | V8: 46175 | W8: =V8-TODAY() -> 20 | X8: 5 | Y8: 50000 | Z8: CE, REACH, AMS 2770 | AA8: Intertek | AB8: Yes
A9: REF-MET-002 | B9: ALU-PRF | C9: Aluminum Profiles | D9: Metals | E9: m | F9: 32 | G9: 38 | H9: 35 | I9: 2 | J9: =G9+I9 -> 40.00 | K9: =IFERROR(ROUND((G9-F9)/F9,4),0) -> 18.8% | L9: Jebel Ali, UAE | M9: Aqaba, Jordan | N9: =L9&" → "&M9 -> Jebel Ali, UAE → Aqaba, Jordan | O9: 8 | P9: FOB | Q9: UAE/China | R9: 0 | S9: =J9*(1+R9) -> 40.00 | T9: TT in advance | U9: 46149 | V9: 46175 | W9: =V9-TODAY() -> 20 | X9: 500 | Y9: 20000 | Z9: CE, REACH | AA9: None | AB9: Yes
A10: REF-MET-003 | B10: CPR-ETP | C10: Copper ETP Rod 8mm | D10: Metals | E10: MT | F10: 8900 | G10: 9800 | H10: 9300 | I10: 90 | J10: =G10+I10 -> 9,890.00 | K10: =IFERROR(ROUND((G10-F10)/F10,4),0) -> 10.1% | L10: Antwerp, Belgium | M10: Jebel Ali, UAE | N10: =L10&" → "&M10 -> Antwerp, Belgium → Jebel Ali, UAE | O10: 10 | P10: CIF | Q10: Chile/UAE | R10: 0 | S10: =J10*(1+R10) -> 9,890.00 | T10: LC at sight | U10: 46148 | V10: 46168 | W10: =V10-TODAY() -> 13 | X10: 5 | Y10: 50000 | Z10: ASTM B187, EN 13599 | AA10: SGS | AB10: Yes
A11: REF-BLD-001 | B11: BLK-200 | C11: Concrete Block 20cm | D11: Building | E11: Unit | F11: 3.8 | G11: 4.8 | H11: 4.2 | I11: 0.3 | J11: =G11+I11 -> 5.10 | K11: =IFERROR(ROUND((G11-F11)/F11,4),0) -> 26.3% | L11: Jebel Ali, UAE | M11: Dubai, UAE | N11: =L11&" → "&M11 -> Jebel Ali, UAE → Dubai, UAE | O11: 3 | P11: DAP | Q11: UAE | R11: 0.05 | S11: =J11*(1+R11) -> 5.36 | T11: TT in advance | U11: 46152 | V11: 46214 | W11: =V11-TODAY() -> 59 | X11: 1000 | Y11: 5000 | Z11: ISO 9001, ASTM C90 | AA11: None | AB11: Yes
A12: REF-BLD-001 | B12: CNC-B25 | C12: Ready-Mix Concrete B25 | D12: Building | E12: m³ | F12: 310 | G12: 380 | H12: 345 | I12: 0 | J12: =G12+I12 -> 380.00 | K12: =IFERROR(ROUND((G12-F12)/F12,4),0) -> 22.6% | L12: Dubai, UAE | M12: Dubai, UAE | N12: =L12&" → "&M12 -> Dubai, UAE → Dubai, UAE | O12: 2 | P12: DAP | Q12: UAE | R12: 0.05 | S12: =J12*(1+R12) -> 399.00 | T12: TT in advance | U12: 46149 | V12: 46161 | W12: =V12-TODAY() -> 6 | X12: 10 | Y12: 5000 | Z12: ISO 9001, BS 8500 | AA12: None | AB12: Yes
A13: REF-BLD-002 | B13: TLE-6060 | C13: Porcelain Tile 60×60cm | D13: Building | E13: m² | F13: 48 | G13: 62 | H13: 55 | I13: 8 | J13: =G13+I13 -> 70.00 | K13: =IFERROR(ROUND((G13-F13)/F13,4),0) -> 29.2% | L13: Genoa, Italy | M13: Jebel Ali, UAE | N13: =L13&" → "&M13 -> Genoa, Italy → Jebel Ali, UAE | O13: 5 | P13: CIF | Q13: Italy/Spain | R13: 0.05 | S13: =J13*(1+R13) -> 73.50 | T13: LC 60 days | U13: 46151 | V13: 46184 | W13: =V13-TODAY() -> 29 | X13: 100 | Y13: 5000 | Z13: ISO 9001, CE | AA13: None | AB13: Yes
A14: REF-BLD-003 | B14: PVC-110 | C14: PVC Pipe 110mm SDR34 | D14: Building | E14: m | F14: 21 | G14: 28 | H14: 25 | I14: 1.5 | J14: =G14+I14 -> 29.50 | K14: =IFERROR(ROUND((G14-F14)/F14,4),0) -> 33.3% | L14: Jebel Ali, UAE | M14: Aqaba, Jordan | N14: =L14&" → "&M14 -> Jebel Ali, UAE → Aqaba, Jordan | O14: 4 | P14: DAP | Q14: UAE/Egypt | R14: 0.05 | S14: =J14*(1+R14) -> 30.98 | T14: TT in advance | U14: 46151 | V14: 46184 | W14: =V14-TODAY() -> 29 | X14: 500 | Y14: 5000 | Z14: CE, ISO 4422 | AA14: None | AB14: Yes
A15: REF-BLD-004 | B15: STL-STR | C15: Structural Steel H-Beam | D15: Building | E15: MT | F15: 2900 | G15: 3200 | H15: 3050 | I15: 48 | J15: =G15+I15 -> 3,248.00 | K15: =IFERROR(ROUND((G15-F15)/F15,4),0) -> 10.3% | L15: Istanbul, Turkey | M15: Alexandria, Egypt | N15: =L15&" → "&M15 -> Istanbul, Turkey → Alexandria, Egypt | O15: 8 | P15: FOB | Q15: Turkey | R15: 0.05 | S15: =J15*(1+R15) -> 3,410.40 | T15: LC at sight | U15: 46148 | V15: 46175 | W15: =V15-TODAY() -> 20 | X15: 10 | Y15: 50000 | Z15: EN 10034, ISO 9001 | AA15: BV | AB15: Yes
A16: REF-ENE-001 | B16: DSL-B2 | C16: Industrial Diesel B2 | D16: Energy | E16: Liter | F16: 3.9 | G16: 4.92 | H16: 4.5 | I16: 0.15 | J16: =G16+I16 -> 5.07 | K16: =IFERROR(ROUND((G16-F16)/F16,4),0) -> 26.2% | L16: Jebel Ali, UAE | M16: Aqaba, Jordan | N16: =L16&" → "&M16 -> Jebel Ali, UAE → Aqaba, Jordan | O16: 2 | P16: DAP | Q16: UAE | R16: 0 | S16: =J16*(1+R16) -> 5.07 | T16: TT in advance | U16: 46152 | V16: 46161 | W16: =V16-TODAY() -> 6 | X16: 5000 | Y16: 25000 | Z16: ISO 14001, EN 590 | AA16: SGS | AB16: Yes
... A29: REF-CHM-003 | B29: HDPE-BLW | C29: HDPE Blow Grade | D29: Chemicals | E29: MT | F29: 1050 | G29: 1220 | H29: 1140 | I29: 50 | J29: =G29+I29 -> 1,270.00 | K29: =IFERROR(ROUND((G29-F29)/F29,4),0) -> 16.2% | L29: Jebel Ali, UAE | M29: Alexandria, Egypt | N29: =L29&" → "&M29 -> Jebel Ali, UAE → Alexandria, Egypt | O29: 10 | P29: CIF | Q29: UAE/Saudi | R29: 0 | S29: =J29*(1+R29) -> 1,270.00 | T29: TT in advance | U29: 46150 | V29: 46184 | W29: =V29-TODAY() -> 29 | X29: 20 | Y29: 20000 | Z29: REACH, RoHS | AA29: None | AB29: Yes
A30: AVERAGES / TOTALS (25 products) | F30: =AVERAGE(F5:F29) -> 1,505.51 | G30: =AVERAGE(G5:G29) -> 1,682.11 | H30: =AVERAGE(H5:H29) -> 1,590.54 | I30: =AVERAGE(I5:I29) -> 33.09 | J30: =AVERAGE(J5:J29) -> 1,715.20 | K30: =AVERAGE(K5:K29) -> 18.2% | S30: =AVERAGE(S5:S29) -> 1,738.54 | Y30: =SUM(Y5:Y29) -> 825,000

Sheet ⚡ Negotiation Params
A1: SLOI AI — Negotiation Parameters per Product
A2: Blue = editable · Green = auto-calc · These parameters drive the Claude negotiation agent
A3: PRODUCT | E3: PRICE ANCHORS | I3: AGENT BEHAVIOR | M3: VOLUME DISCOUNTS | P3: AUTONOMOUS
A4: REF Code | B4: SKU | C4: Product Name | D4: Unit | E4: Market Price $/unit | F4: Walk-Away $/unit | G4: Opening Offer $/unit | H4: Broker Floor $/unit | I4: Max Rounds | J4: Opening Offer % | K4: Concession per Round % | L4: Strategy | M4: Vol Disc 1 (qty / %) | N4: Vol Disc 2 (qty / %) | O4: Vol Disc 3 (qty / %) | P4: Auto-Approve | Q4: Daily Cap (orders) | R4: Daily Cap (USD)
A5: REF-MET-001 | B5: STL-12 | C5: Steel Rebar G60 12mm | D5: MT | E5: 2840 | F5: 2700 | G5: 2960 | H5: 2720 | I5: 5 | J5: 4.5% | K5: 2.0% | L5: standard | M5: 100MT/1% | N5: 500MT/2% | O5: 1000MT/3% | P5: Yes | Q5: 3 | R5: 500000
A6: REF-MET-001 | B6: STL-HRC | C6: Steel HR Coil SS400 | D6: MT | E6: 3100 | F6: 2950 | G6: 3220 | H6: 2950 | I6: 5 | J6: 3.9% | K6: 1.8% | L6: standard | M6: 50MT/1% | N6: 200MT/2% | O6: 500MT/3% | P6: Yes | Q6: 2 | R6: 300000
A7: REF-MET-001 | B7: STL-CRC | C7: Steel CR Coil DC01 | D7: MT | E7: 3400 | F7: 3200 | G7: 3550 | H7: 3220 | I7: 4 | J7: 4.4% | K7: 2.0% | L7: aggressive | M7: 20MT/1% | N7: 100MT/2% | O7: 500MT/3% | P7: No | Q7: 1 | R7: 200000
A8: REF-MET-002 | B8: ALU-6061 | C8: Aluminum 6061-T6 | D8: MT | E8: 9200 | F8: 8800 | G8: 9560 | H8: 8800 | I8: 5 | J8: 3.9% | K8: 1.5% | L8: standard | M8: 5MT/0.5% | N8: 20MT/1% | O8: 100MT/2% | P8: No | Q8: 1 | R8: 100000
A9: REF-MET-002 | B9: ALU-PRF | C9: Aluminum Profiles | D9: m | E9: 38 | F9: 35 | G9: 39.5 | H9: 35 | I9: 4 | J9: 4.0% | K9: 2.0% | L9: standard | M9: 500m/1% | N9: 2000m/2% | O9: 10000m/3% | P9: No | Q9: 1 | R9: 50000
A10: REF-MET-003 | B10: CPR-ETP | C10: Copper ETP Rod 8mm | D10: MT | E10: 9800 | F10: 9300 | G10: 10200 | H10: 9300 | I10: 5 | J10: 4.1% | K10: 1.5% | L10: aggressive | M10: 5MT/0.5% | N10: 20MT/1.5% | O10: 50MT/2.5% | P10: No | Q10: 1 | R10: 150000
A11: REF-BLD-001 | B11: BLK-200 | C11: Concrete Block 20cm | D11: Unit | E11: 4.8 | F11: 4.2 | G11: 5 | H11: 4.2 | I11: 4 | J11: 4.2% | K11: 2.0% | L11: standard | M11: 1000/1% | N11: 5000/2% | O11: 20000/3% | P11: Yes | Q11: 5 | R11: 200000
A12: REF-BLD-001 | B12: CNC-B25 | C12: Ready-Mix Concrete B25 | D12: m³ | E12: 380 | F12: 345 | G12: 395 | H12: 345 | I12: 3 | J12: 3.9% | K12: 2.5% | L12: standard | M12: 10m³/1% | N12: 50m³/2% | O12: 200m³/3% | P12: Yes | Q12: 5 | R12: 100000
A13: REF-BLD-002 | B13: TLE-6060 | C13: Porcelain Tile 60×60cm | D13: m² | E13: 62 | F13: 55 | G13: 64 | H13: 55 | I13: 4 | J13: 3.2% | K13: 1.5% | L13: standard | M13: 100m²/1% | N13: 500m²/2% | O13: 2000m²/3% | P13: No | Q13: 1 | R13: 50000
A14: REF-BLD-003 | B14: PVC-110 | C14: PVC Pipe 110mm | D14: m | E14: 28 | F14: 25 | G14: 29 | H14: 25 | I14: 4 | J14: 3.6% | K14: 2.0% | L14: standard | M14: 500m/1% | N14: 2000m/2% | O14: 10000m/3% | P14: No | Q14: 1 | R14: 30000
A15: REF-BLD-004 | B15: STL-STR | C15: Structural Steel H-Beam | D15: MT | E15: 3200 | F15: 3050 | G15: 3320 | H15: 3050 | I15: 5 | J15: 3.8% | K15: 1.8% | L15: standard | M15: 10MT/1% | N15: 50MT/2% | O15: 200MT/3% | P15: Yes | Q15: 2 | R15: 300000
A16: REF-ENE-001 | B16: DSL-B2 | C16: Industrial Diesel B2 | D16: Liter | E16: 4.92 | F16: 4.5 | G16: 5.1 | H16: 4.5 | I16: 3 | J16: 3.7% | K16: 2.0% | L16: standard | M16: 5000L/1% | N16: 20000L/2% | O16: 100000L/3% | P16: Yes | Q16: 5 | R16: 500000
... A29: REF-CHM-003 | B29: HDPE-BLW | C29: HDPE Blow Grade | D29: MT | E29: 1220 | F29: 1140 | G29: 1270 | H29: 1140 | I29: 5 | J29: 4.1% | K29: 1.5% | L29: standard | M29: 20MT/1% | N29: 100MT/2% | O29: 500MT/3% | P29: No | Q29: 1 | R29: 100000

Sheet 🚢 Trade Routes
A1: SLOI AI — Trade Routes Catalog
A2: Each route = product + origin port + destination port + full cost breakdown · Blue = editable · Green = auto
A3: ROUTE | F3: COST BREAKDOWN ($/unit) | K3: LEAD & TERMS | N3: STATUS
A4: Route ID | B4: Product | C4: Sector | D4: Port of Origin | E4: Port of Destination | F4: Market Price $/unit | G4: Freight $/unit | H4: CIF Price $/unit | I4: Import Duty % | J4: Landed Cost $/unit | K4: Lead Time (days) | L4: Incoterm | M4: Payment Terms | N4: Active
A5: RT-001 | B5: Steel Rebar G60 | C5: Metals | D5: Jebel Ali, UAE | E5: Alexandria, Egypt | F5: 2840 | G5: 45 | H5: =F5+G5 -> 2,885.00 | I5: 0.05 | J5: =H5*(1+I5) -> 3,029.25 | K5: 7 | L5: FOB | M5: LC at sight | N5: Yes
A6: RT-002 | B6: Steel Rebar G60 | C6: Metals | D6: Jebel Ali, UAE | E6: Aqaba, Jordan | F6: 2840 | G6: 52 | H6: =F6+G6 -> 2,892.00 | I6: 0.05 | J6: =H6*(1+I6) -> 3,036.60 | K6: 8 | L6: FOB | M6: LC at sight | N6: Yes
A7: RT-003 | B7: Steel Rebar G60 | C7: Metals | D7: Jebel Ali, UAE | E7: Haifa, Israel | F7: 2840 | G7: 38 | H7: =F7+G7 -> 2,878.00 | I7: 0 | J7: =H7*(1+I7) -> 2,878.00 | K7: 6 | L7: FOB | M7: TT in advance | N7: Yes
A8: RT-004 | B8: Steel Rebar G60 | C8: Metals | D8: Istanbul, Turkey | E8: Alexandria, Egypt | F8: 2840 | G8: 42 | H8: =F8+G8 -> 2,882.00 | I8: 0.05 | J8: =H8*(1+I8) -> 3,026.10 | K8: 7 | L8: FOB | M8: LC at sight | N8: Yes
A9: RT-005 | B9: Steel HR Coil | C9: Metals | D9: Jebel Ali, UAE | E9: Port Said, Egypt | F9: 3100 | G9: 55 | H9: =F9+G9 -> 3,155.00 | I9: 0.05 | J9: =H9*(1+I9) -> 3,312.75 | K9: 10 | L9: FOB | M9: LC at sight | N9: Yes
A10: RT-006 | B10: Steel HR Coil | C10: Metals | D10: Hamburg, Germany | E10: Jebel Ali, UAE | F10: 3100 | G10: 75 | H10: =F10+G10 -> 3,175.00 | I10: 0 | J10: =H10*(1+I10) -> 3,175.00 | K10: 14 | L10: FOB | M10: LC 30 days | N10: Yes
A11: RT-007 | B11: Aluminum 6061-T6 | C11: Metals | D11: Jebel Ali, UAE | E11: Haifa, Israel | F11: 9200 | G11: 75 | H11: =F11+G11 -> 9,275.00 | I11: 0 | J11: =H11*(1+I11) -> 9,275.00 | K11: 8 | L11: FOB | M11: TT in advance | N11: Yes
A12: RT-008 | B12: Aluminum 6061-T6 | C12: Metals | D12: Jebel Ali, UAE | E12: Aqaba, Jordan | F12: 9200 | G12: 82 | H12: =F12+G12 -> 9,282.00 | I12: 0 | J12: =H12*(1+I12) -> 9,282.00 | K12: 9 | L12: FOB | M12: TT in advance | N12: Yes
A13: RT-009 | B13: Copper ETP Rod | C13: Metals | D13: Antwerp, Belgium | E13: Jebel Ali, UAE | F13: 9800 | G13: 90 | H13: =F13+G13 -> 9,890.00 | I13: 0 | J13: =H13*(1+I13) -> 9,890.00 | K13: 12 | L13: CIF | M13: LC at sight | N13: Yes
A14: RT-010 | B14: Concrete Block 20cm | C14: Building | D14: Jebel Ali, UAE | E14: Dubai, UAE | F14: 4.8 | G14: 0.3 | H14: =F14+G14 -> 5.10 | I14: 0.05 | J14: =H14*(1+I14) -> 5.36 | K14: 3 | L14: DAP | M14: TT in advance | N14: Yes
A15: RT-011 | B15: Concrete Block 20cm | C15: Building | D15: Jebel Ali, UAE | E15: Muscat, Oman | F15: 4.8 | G15: 0.5 | H15: =F15+G15 -> 5.30 | I15: 0.05 | J15: =H15*(1+I15) -> 5.57 | K15: 4 | L15: DAP | M15: TT in advance | N15: Yes
A16: RT-012 | B16: Porcelain Tile 60×60 | C16: Building | D16: Genoa, Italy | E16: Jebel Ali, UAE | F16: 62 | G16: 8 | H16: =F16+G16 -> 70.00 | I16: 0.05 | J16: =H16*(1+I16) -> 73.50 | K16: 12 | L16: CIF | M16: LC 60 days | N16: Yes
... A34: RT-030 | B34: PP Granules | C34: Chemicals | D34: Jebel Ali, UAE | E34: Haifa, Israel | F34: 1280 | G34: 55 | H34: =F34+G34 -> 1,335.00 | I34: 0 | J34: =H34*(1+I34) -> 1,335.00 | K34: 8 | L34: CIF | M34: TT in advance | N34: Yes
A35: 30 routes · Use Route Calculator for CIF quotes | F35: =AVERAGE(F5:F34) -> 2,119.71 | G35: =AVERAGE(G5:G34) -> 39.07 | H35: =AVERAGE(H5:H34) -> 2,158.79 | J35: =AVERAGE(J5:J34) -> 2,193.62

Sheet 🚢 Port Reference
A1: SLOI AI — Port Reference & Shipping Routes
A2: Port Name | B2: Country | C2: Region | D2: Typical Lead +Days | E2: Notes
A3: Jebel Ali, UAE | B3: UAE | C3: Gulf | D3: +0 days | E3: Main SLOI AI hub · largest port MENA
A4: Fujairah, UAE | B4: UAE | C4: Gulf/Indian | D4: +1 days | E4: Bunkering · oil products
A5: Abu Dhabi, UAE | B5: UAE | C5: Gulf | D5: +1 days | E5: ADNOC products · chemicals
A6: Alexandria, Egypt | B6: Egypt | C6: Mediterranean | D6: +4 days | E6: Main Egypt import port
A7: Port Said, Egypt | B7: Egypt | C7: Suez Canal | D7: +4 days | E7: Transit · bulk cargo
A8: Suez, Egypt | B8: Egypt | C8: Red Sea | D8: +5 days | E8: Canal entry · chemicals
A9: Aqaba, Jordan | B9: Jordan | C9: Red Sea | D9: +3 days | E9: Jordan only landlocked port
A10: Haifa, Israel | B10: Israel | C10: Mediterranean | D10: +3 days | E10: Main Israeli port
A11: Ashdod, Israel | B11: Israel | C11: Mediterranean | D11: +3 days | E11: Bulk · containers
A12: Jeddah, KSA | B12: Saudi Arabia | C12: Red Sea | D12: +2 days | E12: Main KSA port
A13: Dammam, KSA | B13: Saudi Arabia | C13: Gulf | D13: +2 days | E13: Eastern Province
... A24: Djibouti | B24: Djibouti | C24: Red Sea | D24: +5 days | E24: Horn of Africa hub

Sheet 🌍 Broker Floors
A1: SLOI AI — Broker Floor Prices
A2: Floor = Market Price × (1 - Discount%) · Blue = editable · Green = auto-calculated
A3: Broker ID | B3: Name | C3: Country | D3: Sectors | E3: Discount% | F3: Preferred Ports | G3: STL-12 Floor | H3: WHT-HRD Floor | I3: H2SO4 Floor | J3: Status
A4: BRK-UAE-001 | B4: Gulf Trade Partners | C4: UAE | D4: Metals · Building | E4: 0.05 | F4: Jebel Ali → Alexandria / Aqaba | G4: =2840*(1-E4) -> 2,698.00 | H4: =1120*(1-E4) -> 1,064.00 | I4: =580*(1-E4) -> 551.00 | J4: Active
A5: BRK-EUR-001 | B5: EuroChem GmbH | C5: Germany | D5: Agriculture · Chemicals | E5: 0.04 | F5: Hamburg/Antwerp → Jebel Ali | G5: =2840*(1-E5) -> 2,726.40 | H5: =1120*(1-E5) -> 1,075.20 | I5: =580*(1-E5) -> 556.80 | J5: Active
A6: BRK-EGY-001 | B6: MENA Commodities | C6: Egypt | D6: Building · Agriculture | E6: 0.06 | F6: Jebel Ali → Port Said | G6: =2840*(1-E6) -> 2,669.60 | H6: =1120*(1-E6) -> 1,052.80 | I6: =580*(1-E6) -> 545.20 | J6: Active
A7: BRK-KSA-001 | B7: Arabian Trade Co. | C7: Saudi Arabia | D7: Metals · Energy | E7: 0.05 | F7: Jebel Ali → Jeddah/Dammam | G7: =2840*(1-E7) -> 2,698.00 | H7: =1120*(1-E7) -> 1,064.00 | I7: =580*(1-E7) -> 551.00 | J7: Active
A8: BRK-JOR-001 | B8: Jordan Import Partners | C8: Jordan | D8: Agriculture · Building | E8: 0.04 | F8: Jebel Ali → Aqaba | G8: =2840*(1-E8) -> 2,726.40 | H8: =1120*(1-E8) -> 1,075.20 | I8: =580*(1-E8) -> 556.80 | J8: Active

Sheet 📊 Dashboard
A1: SLOI AI — Product Catalog Dashboard
A3: Total Products | C3: Active Products
A4: =COUNTA('📦 Product Catalog'!C5:C29) -> 25 | C4: =COUNTIF('📦 Product Catalog'!AB5:AB29,"Yes") -> 25
A5: Avg Market Price | C5: Avg Margin
A6: =AVERAGE('📦 Product Catalog'!G5:G29) -> 1,682.11 | C6: =AVERAGE('📦 Product Catalog'!K5:K29) -> 18.2%
A7: Avg Freight $/unit | C7: Avg Duty %
A8: =AVERAGE('📦 Product Catalog'!I5:I29) -> 33.09 | C8: =AVERAGE('📦 Product Catalog'!R5:R29) -> 2%
A9: Expiring ≤7 days | C9: Total Brokers
A10: =COUNTIF('📦 Product Catalog'!W5:W29,"<=7") -> 4 | C10: =COUNTA('🌍 Broker Floors'!A4:A8) -> 5

Sheet ℹ️ Legend
A1: SLOI AI — Field Definitions
A2: FIELD / COLOR | B2: DEFINITION
A3: REF Code | B3: Internal supplier reference. Never shown to buyers. RLS-enforced in DB.
A4: SKU | B4: Stock Keeping Unit — use in API calls (product_ref parameter)
A5: Cost Price 🔵 | B5: SLOI AI purchase/known cost. Confidential. Blue = editable.
A6: Market Price 🔵 | B6: Price shown on Exchange and to buyers. Update weekly. Blue = editable.
A7: Broker Floor 🔵 | B7: Minimum price agent can negotiate to. Blue = editable.
A8: Freight $/unit 🔵 | B8: Estimated shipping cost per unit on main route. Blue = editable.
A9: CIF Price 🟢 | B9: Auto: Market Price + Freight. Green = formula, do not edit.
A10: Margin % 🟢 | B10: Auto: (Market - Cost) / Cost. Green ≥20% · Yellow 10-20% · Red <10%
A11: Port of Origin 🔵 | B11: Main departure port for this product (e.g. Jebel Ali, UAE)
A12: Port of Destination 🔵 | B12: Default destination port (e.g. Alexandria, Egypt). Override per deal.
A13: Shipping Route 🟢 | B13: Auto: Port of Origin → Port of Destination. Formula.
... A27: 🔵 Blue port cells | B27: Port fields — editable
